horuslp/__init__.py
horuslp/core/Constraint.py
horuslp/core/Metric.py
horuslp/core/Objective.py
horuslp/core/ProblemClass.py
horuslp/core/Variables.py
horuslp/core/__init__.py
horuslp/core/constants.py
horuslp/core/utils.py
horuslp-0.0.7.dist-info/LICENSE
horuslp-0.0.7.dist-info/METADATA
horuslp-0.0.7.dist-info/WHEEL
horuslp-0.0.7.dist-info/top_level.txt
horuslp-0.0.7.dist-info/RECORD
